atai/__init__.py
atai/_modidx.py
atai/core.py
atai-0.0.6.dist-info/LICENSE
atai-0.0.6.dist-info/METADATA
atai-0.0.6.dist-info/WHEEL
atai-0.0.6.dist-info/entry_points.txt
atai-0.0.6.dist-info/top_level.txt
atai-0.0.6.dist-info/RECORD
