Metadata-Version: 2.1
Name: atai
Version: 0.0.6
Summary: Atomic AI – An attempt at a minimalist, flexible deep learning framework for diverse models.
Home-page: https://github.com/frenio/atai
Author: Frenio Redeker
Author-email: f.redeker@gmail.com
License: Apache Software License 2.0
Keywords: nbdev jupyter notebook python
Classifier: Development Status :: 4 - Beta
Classifier: Intended Audience :: Developers
Classifier: Natural Language :: English
Classifier: Programming Language :: Python :: 3.7
Classifier: Programming Language :: Python :: 3.8
Classifier: Programming Language :: Python :: 3.9
Classifier: Programming Language :: Python :: 3.10
Classifier: License :: OSI Approved :: Apache Software License
Requires-Python: >=3.7
License-File: LICENSE
Requires-Dist: matplotlib
Requires-Dist: numpy
Requires-Dist: torch
Requires-Dist: torcheval
Requires-Dist: torchmetrics
Requires-Dist: fastcore
Requires-Dist: fastprogress
Provides-Extra: dev
